kommander/__init__.py
kommander/config.py
kommander/context.py
kommander/core.py
kommander/main.py
kommander/ui.py
kommander_cli-1.0.1.dist-info/licenses/LICENSE.md
kommander_cli-1.0.1.dist-info/METADATA
kommander_cli-1.0.1.dist-info/WHEEL
kommander_cli-1.0.1.dist-info/entry_points.txt
kommander_cli-1.0.1.dist-info/top_level.txt
kommander_cli-1.0.1.dist-info/RECORD
