Metadata-Version: 2.4
Name: kommander-cli
Version: 1.0.1
Summary: A command-line companion that translates natural language into safe, executable shell commands.
Author: The Kommander Authors
License: MIT
Project-URL: Homepage, https://github.com/debacodes10/Kommander
Project-URL: Bug Tracker, https://github.com/debacodes10/Kommander/issues
Classifier: Programming Language :: Python :: 3
Classifier: Programming Language :: Python :: 3.9
Classifier: Programming Language :: Python :: 3.10
Classifier: Programming Language :: Python :: 3.11
Classifier: Programming Language :: Python :: 3.12
Classifier: License :: OSI Approved :: MIT License
Classifier: Operating System :: OS Independent
Classifier: Environment :: Console
Classifier: Topic :: Utilities
Requires-Python: >=3.9
License-File: LICENSE.md
Requires-Dist: typer[all]>=0.9.0
Requires-Dist: rich>=13.0.0
Requires-Dist: google-generativeai>=0.4.0
Requires-Dist: pyperclip>=1.8.2
Provides-Extra: dev
Requires-Dist: pytest>=7.0.0; extra == "dev"
Dynamic: license-file
